{
  "_comment": "Mapping intent cho từng câu FAQ. Key = '<slug>'/'<question_number>'. Sửa file này khi thêm/đổi intent. Chạy build_faq_index.py để regen catalog.",
  "_updated": "2026-04-23",

  "_intents_definition": {
    "SO_SANH":    "So sánh & Ra quyết định (so sánh phiên bản, đối thủ, đáng mua không)",
    "VAN_HANH":   "Vận hành & Trải nghiệm lái (động cơ, hộp số, cách âm, cảm giác lái)",
    "TIEU_HAO":   "Mức tiêu hao nhiên liệu (xăng/dầu/điện, chi phí vận hành)",
    "NGOAI_THAT": "Ngoại thất & Kích thước (form dáng, gầm, mâm, đèn, màu)",
    "NOI_THAT":   "Nội thất & Không gian (ghế, màn hình, âm thanh, điều hòa)",
    "AN_TOAN":    "Hệ thống an toàn (túi khí, ADAS, camera, bảo hành)",
    "NHU_CAU":    "Sự phù hợp với nhu cầu (gia đình, dịch vụ, đô thị, đi tỉnh)"
  },

  "kia-k5": {
    "1":  ["VAN_HANH", "NGOAI_THAT"],
    "2":  ["AN_TOAN", "SO_SANH"],
    "3":  ["VAN_HANH", "TIEU_HAO", "SO_SANH"],
    "4":  ["VAN_HANH", "NOI_THAT"],
    "5":  ["SO_SANH", "NHU_CAU"],
    "6":  ["SO_SANH", "NGOAI_THAT"],
    "7":  ["SO_SANH"],
    "8":  ["SO_SANH"],
    "9":  ["NOI_THAT"],
    "10": ["SO_SANH"]
  },

  "kia-sportage": {
    "1":  ["SO_SANH", "AN_TOAN"],
    "2":  ["SO_SANH"],
    "3":  ["AN_TOAN"],
    "4":  ["VAN_HANH", "AN_TOAN", "SO_SANH"],
    "5":  ["SO_SANH"],
    "6":  ["SO_SANH"],
    "7":  ["SO_SANH"],
    "8":  ["NOI_THAT", "SO_SANH"],
    "9":  ["VAN_HANH"],
    "10": ["VAN_HANH", "TIEU_HAO"],
    "11": ["NOI_THAT"],
    "12": ["SO_SANH"],
    "13": ["VAN_HANH"]
  },

  "kia-new-sorento": {
    "1":  ["VAN_HANH", "TIEU_HAO", "SO_SANH"],
    "2":  ["VAN_HANH", "TIEU_HAO"],
    "3":  ["VAN_HANH", "NOI_THAT"],
    "4":  ["SO_SANH", "VAN_HANH", "TIEU_HAO"],
    "5":  ["SO_SANH"],
    "6":  ["AN_TOAN", "NOI_THAT"],
    "7":  ["VAN_HANH"],
    "8":  ["VAN_HANH"],
    "9":  ["AN_TOAN", "SO_SANH"],
    "10": ["AN_TOAN", "SO_SANH"],
    "11": ["SO_SANH"]
  },

  "kia-sorento-hybrid": {
    "1":  ["AN_TOAN", "SO_SANH"],
    "2":  ["TIEU_HAO", "SO_SANH"],
    "3":  ["AN_TOAN", "VAN_HANH"],
    "4":  ["VAN_HANH"],
    "5":  ["VAN_HANH", "TIEU_HAO"],
    "6":  ["VAN_HANH", "TIEU_HAO"],
    "7":  ["VAN_HANH", "AN_TOAN"],
    "8":  ["VAN_HANH", "TIEU_HAO"],
    "9":  ["SO_SANH", "VAN_HANH"],
    "10": ["SO_SANH", "TIEU_HAO"],
    "11": ["VAN_HANH", "SO_SANH"]
  },

  "kia-new-carnival": {
    "1": ["SO_SANH", "AN_TOAN", "NOI_THAT", "NGOAI_THAT"],
    "2": ["SO_SANH", "AN_TOAN", "NOI_THAT", "NGOAI_THAT"]
  }
}
